aiosaber/__init__.py
aiosaber/channel.py
aiosaber/component.py
aiosaber/context.py
aiosaber/flow.py
aiosaber/middleware.py
aiosaber/operators.py
aiosaber/task.py
aiosaber/utility/__init__.py
aiosaber/utility/dask_executor.py
aiosaber/utility/scheduler.py
aiosaber/utility/target.py
aiosaber/utility/typings.py
aiosaber/utility/utils.py
aiosaber-0.0.1.1.dist-info/LICENSE
aiosaber-0.0.1.1.dist-info/METADATA
aiosaber-0.0.1.1.dist-info/WHEEL
aiosaber-0.0.1.1.dist-info/top_level.txt
aiosaber-0.0.1.1.dist-info/RECORD
