Metadata-Version: 2.1
Name: aiosaber
Version: 0.0.1.1
Summary: A concurrent streaming package
Home-page: https://github.com/flowsaber/aiosaber
Author: bakezq
Author-email: zhongquan789@gmail.com
License: MIT
Keywords: dataflow,asyncio
Platform: UNKNOWN
Classifier: Development Status :: 3 - Alpha
Classifier: Operating System :: POSIX
Classifier: Programming Language :: Python
Classifier: Programming Language :: Python :: 3
Classifier: Programming Language :: Python :: 3.7
Classifier: Programming Language :: Python :: 3.8
Classifier: Programming Language :: Python :: 3.9
Classifier: License :: OSI Approved :: MIT License
Classifier: Intended Audience :: Science/Research
Classifier: Topic :: Software Development :: Libraries
Requires-Python: >=3.7, <4
Requires-Dist: uvloop
Requires-Dist: makefun
Requires-Dist: dask
Requires-Dist: distributed
